testing/fixtures/__init__.py
testing/fixtures/py.typed
testing/fixtures/utils/__init__.py
testing_fixtures-0.4.1.dist-info/METADATA
testing_fixtures-0.4.1.dist-info/WHEEL
testing_fixtures-0.4.1.dist-info/RECORD
