Metadata-Version: 2.1
Name: testing-fixtures
Version: 0.4.1
Summary: New approach to Python test fixtures (compatible with pytest)
Project-URL: Homepage, https://github.com/abid-mujtaba/testing-fixtures
Author-email: "Abid H. Mujtaba" <abid.naqvi83@gmail.com>
Keywords: fixture,fixtures,testing,tests
Classifier: License :: OSI Approved :: MIT License
Classifier: Operating System :: OS Independent
Classifier: Programming Language :: Python :: 3
Requires-Python: >=3.8
Requires-Dist: typing-extensions
Provides-Extra: dev
Requires-Dist: black; extra == 'dev'
Requires-Dist: mypy; extra == 'dev'
Requires-Dist: pylint; extra == 'dev'
Requires-Dist: pytest; extra == 'dev'
